typing.py
typing-3.7.4.2.dist-info/LICENSE
typing-3.7.4.2.dist-info/METADATA
typing-3.7.4.2.dist-info/WHEEL
typing-3.7.4.2.dist-info/top_level.txt
typing-3.7.4.2.dist-info/RECORD
