Metadata-Version: 2.1
Name: typing
Version: 3.7.4.2
Summary: Type Hints for Python
Home-page: https://docs.python.org/3/library/typing.html
Author: Guido van Rossum, Jukka Lehtosalo, Łukasz Langa, Ivan Levkivskyi
Author-email: jukka.lehtosalo@iki.fi
License: PSF
Project-URL: Source, https://github.com/python/typing
Keywords: typing function annotations type hints hinting checking checker typehints typehinting typechecking backport
Platform: UNKNOWN
Classifier: Development Status :: 5 - Production/Stable
Classifier: Environment :: Console
Classifier: Intended Audience :: Developers
Classifier: License :: OSI Approved :: Python Software Foundation License
Classifier: Operating System :: OS Independent
Classifier: Programming Language :: Python :: 2.7
Classifier: Programming Language :: Python :: 3.4
Classifier: Topic :: Software Development
Requires-Python: >=2.7, !=3.0.*, !=3.1.*, !=3.2.*, !=3.3.*, <3.5
